logchain/__init__.py
logchain/formatters/Basic.py
logchain/formatters/Json.py
logchain/formatters/__init__.py
logchain-1.0.0.dist-info/LICENSE
logchain-1.0.0.dist-info/WHEEL
logchain-1.0.0.dist-info/METADATA
logchain-1.0.0.dist-info/RECORD
