Metadata-Version: 2.1
Name: logchain
Version: 1.0.0
Summary: Python logging secured by blockchain
Home-page: https://gitlab.com/ggpack/logchain-py
License: ISC
Keywords: logging,security,blockchain,signature
Author: Gg Math
Author-email: code@gmath.io
Requires-Python: >=3.2,<4.0
Classifier: License :: OSI Approved
Classifier: Programming Language :: Python :: 3
Classifier: Programming Language :: Python :: 3.4
Classifier: Programming Language :: Python :: 3.5
Classifier: Programming Language :: Python :: 3.6
Classifier: Programming Language :: Python :: 3.7
Classifier: Programming Language :: Python :: 3.8
Classifier: Programming Language :: Python :: 3.9
Project-URL: Repository, https://gitlab.com/ggpack/logchain-py
